setup.py
src/rdvac1.py
src/rdvac1.egg-info/PKG-INFO
src/rdvac1.egg-info/SOURCES.txt
src/rdvac1.egg-info/dependency_links.txt
src/rdvac1.egg-info/top_level.txt