Metadata-Version: 1.0
Name: rdvac1
Version: 0.0.1
Summary: An Uber Rides Clustering
Home-page: UNKNOWN
Author: Lagisetty Ravikiran
Author-email: kiranlravi8@gmail.com
License: UNKNOWN
Platform: UNKNOWN
